raspiot/Component.py
raspiot/Pipeline.py
raspiot/Worker.py
raspiot/__init__.py
raspiot-0.1.4.dist-info/LICENSE
raspiot-0.1.4.dist-info/METADATA
raspiot-0.1.4.dist-info/WHEEL
raspiot-0.1.4.dist-info/top_level.txt
raspiot-0.1.4.dist-info/RECORD
