Metadata-Version: 2.1
Name: raspiot
Version: 0.1.4
Summary: A framework for IoT project running on Raspberry Pi
Home-page: https://github.com/newb1er/raspiot
Author: newb1er
Author-email: 32424677+newb1er@users.noreply.github.com
License: UNKNOWN
Platform: UNKNOWN
Classifier: Programming Language :: Python :: 3
Classifier: License :: OSI Approved :: MIT License
Classifier: Operating System :: OS Independent
Requires-Python: >=3.6
License-File: LICENSE
